electronsourcecontroller2/__init__.py
electronsourcecontroller2/eguncom.py
electronsourcecontroller2/egungui.py
electronsourcecontroller2/egunmqttbridge.py
electronsourcecontroller2/mqttpattern.py
electronsourcecontroller2_tspspi-0.0.48.dist-info/LICENSE.md
electronsourcecontroller2_tspspi-0.0.48.dist-info/METADATA
electronsourcecontroller2_tspspi-0.0.48.dist-info/WHEEL
electronsourcecontroller2_tspspi-0.0.48.dist-info/top_level.txt
electronsourcecontroller2_tspspi-0.0.48.dist-info/RECORD
