Metadata-Version: 2.1
Name: electronsourcecontroller2-tspspi
Version: 0.0.48
Summary: Python library and CLI for our custom electron gun slow-control system
Home-page: https://github.com/tspspi/electronSourceController2
Author: Thomas Spielauer
Author-email: pypipackages01@tspi.at
Classifier: Programming Language :: Python :: 3
Classifier: License :: OSI Approved :: BSD License
Classifier: Operating System :: OS Independent
Requires-Python: >=3.6
License-File: LICENSE.md
Requires-Dist: pyserial >=3.4
Requires-Dist: paho-mqtt >=1.6.1
Requires-Dist: daemonize >=2.5.0
Requires-Dist: lockfile >=0.12.2
